torchmetagen/__init__.py
torchmetagen/datasets/__init__.py
torchmetagen/datasets/metagenomicdataset.py
torchmetagen/datasets/utils.py
torchmetagen/models/__init__.py
torchmetagen/models/deepvirfinder.py
torchmetagen/models/utils.py
torchmetagen/models/viraminer.py
torchmetagen/transforms/__init__.py
torchmetagen/transforms/transforms.py
torchmetagen-0.1.8.dist-info/LICENSE.txt
torchmetagen-0.1.8.dist-info/METADATA
torchmetagen-0.1.8.dist-info/WHEEL
torchmetagen-0.1.8.dist-info/top_level.txt
torchmetagen-0.1.8.dist-info/RECORD
